<?xml version="1.0"?>
<!--Generated with glade3 3.4.3 on Sat Feb 28 17:40:51 2009 -->
<interface>
  <object class="GtkAdjustment" id="adjustment1">
    <property name="upper">100</property>
    <property name="lower">1</property>
    <property name="page_increment">10</property>
    <property name="step_increment">1</property>
    <property name="page_size">10</property>
    <property name="value">10</property>
  </object>
  <object class="GtkWindow" id="gtk-facemanager">
    <property name="title" translatable="yes">Face Manager</property>
    <property name="resizable">False</property>
    <property name="window_position">GTK_WIN_POS_CENTER_ALWAYS</property>
    <property name="deletable">False</property>
    <child>
      <object class="GtkHBox" id="hbox1">
        <property name="visible">True</property>
        <child>
          <object class="GtkVBox" id="vbox2">
            <property name="visible">True</property>
            <child>
              <object class="GtkScrolledWindow" id="gtkScroll">
                <property name="visible">True</property>
                <property name="can_focus">True</property>
                <property name="hscrollbar_policy">GTK_POLICY_NEVER</property>
                <child>
                  <object class="GtkIconView" id="gtkIconView">
                    <property name="width_request">280</property>
                    <property name="height_request">300</property>
                    <property name="visible">True</property>
                    <property name="can_focus">True</property>
                    <property name="spacing">2</property>
                    <signal handler="view_onButtonPressed" name="button_press_event"/>
                  </object>
                </child>
              </object>
              <packing>
                <property name="padding">6</property>
              </packing>
            </child>
          </object>
          <packing>
            <property name="padding">6</property>
          </packing>
        </child>
        <child>
          <object class="GtkVBox" id="vbox1">
            <property name="visible">True</property>
            <child>
              <object class="GtkImage" id="gtkWebcamImage">
                <property name="width_request">320</property>
                <property name="height_request">240</property>
                <property name="visible">True</property>
                <property name="stock">gtk-missing-image</property>
                <signal handler="view_onButtonPressed" name="button_press_event"/>
              </object>
              <packing>
                <property name="expand">False</property>
                <property name="fill">False</property>
                <property name="padding">7</property>
              </packing>
            </child>
            <child>
              <object class="GtkHButtonBox" id="hbuttonbox2">
                <property name="visible">True</property>
                <property name="layout_style">GTK_BUTTONBOX_CENTER</property>
                <child>
                  <object class="GtkButton" id="gtkAbout">
                    <property name="visible">True</property>
                    <property name="can_focus">True</property>
                    <property name="receives_default">True</property>
                    <property name="label" translatable="yes">gtk-about</property>
                    <property name="use_stock">True</property>
                    <signal handler="on_gtkAbout_clicked" name="clicked"/>
                  </object>
                </child>
                <child>
                  <object class="GtkSpinButton" id="gtkCountFace">
                    <property name="visible">True</property>
                    <property name="can_focus">True</property>
                    <property name="adjustment">adjustment1</property>
                  </object>
                  <packing>
                    <property name="position">1</property>
                  </packing>
                </child>
                <child>
                  <object class="GtkButton" id="gtkCaptureFace">
                    <property name="visible">True</property>
                    <property name="can_focus">True</property>
                    <property name="receives_default">True</property>
                    <property name="label" translatable="yes">Capture</property>
                    <signal handler="gtkCaptureFace_clicked_cb" name="clicked"/>
                  </object>
                  <packing>
                    <property name="expand">False</property>
                    <property name="position">2</property>
                  </packing>
                </child>
                <child>
                  <object class="GtkButton" id="gtkSave">
                    <property name="visible">True</property>
                    <property name="can_focus">True</property>
                    <property name="receives_default">True</property>
                    <property name="label" translatable="yes">gtk-save</property>
                    <property name="use_stock">True</property>
                    <signal handler="on_gtkSave_clicked" name="clicked"/>
                  </object>
                  <packing>
                    <property name="position">3</property>
                  </packing>
                </child>
              </object>
              <packing>
                <property name="expand">False</property>
                <property name="fill">False</property>
                <property name="position">1</property>
              </packing>
            </child>
            <child>
              <object class="GtkVBox" id="vbox3">
                <property name="visible">True</property>
                <child>
                  <object class="GtkLabel" id="gtkWelcome">
                    <property name="visible">True</property>
                    <property name="justify">GTK_JUSTIFY_CENTER</property>
                  </object>
                  <packing>
                    <property name="expand">False</property>
                    <property name="padding">12</property>
                  </packing>
                </child>
              </object>
              <packing>
                <property name="expand">False</property>
                <property name="fill">False</property>
                <property name="position">2</property>
              </packing>
            </child>
          </object>
          <packing>
            <property name="expand">False</property>
            <property name="fill">False</property>
            <property name="padding">6</property>
            <property name="position">1</property>
          </packing>
        </child>
      </object>
    </child>
  </object>
</interface>
